wykop_sdk_reloaded/__init__.py
wykop_sdk_reloaded/exceptions.py
wykop_sdk_reloaded/v3/__init__.py
wykop_sdk_reloaded/v3/_auth.py
wykop_sdk_reloaded/v3/_request.py
wykop_sdk_reloaded/v3/_urls.py
wykop_sdk_reloaded/v3/_utils.py
wykop_sdk_reloaded/v3/client.py
wykop_sdk_reloaded/v3/types.py
wykop_sdk_reloaded-0.7.0.dist-info/licenses/LICENSE
wykop_sdk_reloaded-0.7.0.dist-info/METADATA
wykop_sdk_reloaded-0.7.0.dist-info/WHEEL
wykop_sdk_reloaded-0.7.0.dist-info/top_level.txt
wykop_sdk_reloaded-0.7.0.dist-info/RECORD
