Metadata-Version: 2.4
Name: wykop_sdk_reloaded
Version: 0.7.0
Summary: Wykop SDK for APIv3 and above.
Author-email: Łukasz Klim <lukasz.klim92@gmail.com>
Project-URL: Homepage, https://github.com/lukas346/wykop_sdk_reloaded
Project-URL: Issues, https://github.com/lukas346/wykop_sdk_reloaded/issues
Classifier: Programming Language :: Python :: 3
Classifier: Programming Language :: Python :: 3.10
Classifier: Programming Language :: Python :: 3.11
Classifier: Programming Language :: Python :: 3.12
Classifier: Programming Language :: Python :: 3.13
Classifier: Operating System :: OS Independent
Requires-Python: >=3.10
License-File: LICENSE
Requires-Dist: requests>=2.31.0
Dynamic: license-file
